pltviz/__init__.py
pltviz/bar.py
pltviz/comp_line.py
pltviz/gini.py
pltviz/legend.py
pltviz/pie.py
pltviz/semipie.py
pltviz/utils.py
pltviz-1.0.1.dist-info/LICENSE.txt
pltviz-1.0.1.dist-info/METADATA
pltviz-1.0.1.dist-info/WHEEL
pltviz-1.0.1.dist-info/top_level.txt
pltviz-1.0.1.dist-info/RECORD
