Metadata-Version: 2.1
Name: pltviz
Version: 1.0.1
Summary: Standardized plots and visualizations in Python
Home-page: https://github.com/andrewtavis/pltviz
Author: Andrew Tavis McAllister
Author-email: andrew.t.mcallister@gmail.com
License: new BSD
Platform: UNKNOWN
Classifier: Development Status :: 5 - Production/Stable
Classifier: Intended Audience :: Developers
Classifier: Intended Audience :: Education
Classifier: Intended Audience :: Science/Research
Classifier: License :: OSI Approved :: BSD License
Classifier: Programming Language :: Python
Classifier: Programming Language :: Python :: 3
Classifier: Programming Language :: Python :: 3.6
Classifier: Programming Language :: Python :: 3.7
Classifier: Programming Language :: Python :: 3.8
Classifier: Operating System :: OS Independent
Requires-Python: >=3.6
Requires-Dist: black (>=19.10b0)
Requires-Dist: certifi (>=2020.12.5)
Requires-Dist: colormath (>=3.0.0)
Requires-Dist: matplotlib (>=3.3.2)
Requires-Dist: numpy (>=1.19.2)
Requires-Dist: packaging (>=20.9)
Requires-Dist: pandas (>=1.2.1)
Requires-Dist: poli-sci-kit (>=0.1.2.7)
Requires-Dist: pytest (>=6.2.2)
Requires-Dist: pytest-cov (>=2.11.1)
Requires-Dist: scipy (>=1.6.0)
Requires-Dist: seaborn (>=0.11.1)
